roxyai_inspect/__init__.py
roxyai_inspect/__main__.py
roxyai_inspect/inspect_server.py
roxyai_inspect/launch.py
roxyai_inspect/roxy_lic_info.exe
roxyai_inspect/version
roxyai_inspect/analysis/__init__.py
roxyai_inspect/analysis/analyze_server.py
roxyai_inspect/analysis/com_definition.py
roxyai_inspect/analysis/command_manager.py
roxyai_inspect/analysis/handler/__init__.py
roxyai_inspect/analysis/handler/echo.py
roxyai_inspect/analysis/handler/get_image.py
roxyai_inspect/analysis/handler/get_probabilities.py
roxyai_inspect/anormal/AnnoPredMatcher.py
roxyai_inspect/anormal/AnormalDetector.py
roxyai_inspect/anormal/BestCnn.py
roxyai_inspect/anormal/CNNTrainer.py
roxyai_inspect/anormal/ClassifierModel.py
roxyai_inspect/anormal/ClassifierTrainer.py
roxyai_inspect/anormal/CustomObjects.py
roxyai_inspect/anormal/DataLoader.py
roxyai_inspect/anormal/Metrics.py
roxyai_inspect/anormal/Model.py
roxyai_inspect/anormal/ModelPairManager.py
roxyai_inspect/anormal/ParamScheduler.py
roxyai_inspect/anormal/Predictor.py
roxyai_inspect/anormal/__init__.py
roxyai_inspect/anormal/cleanser/AutoCleanser.py
roxyai_inspect/anormal/cleanser/CleansingStrategy.py
roxyai_inspect/anormal/cleanser/__init__.py
roxyai_inspect/anormal/evaluator/__init__.py
roxyai_inspect/anormal/evaluator/area_probability.py
roxyai_inspect/anormal/evaluator/evaluator.py
roxyai_inspect/anormal/evaluator/image_matcher.py
roxyai_inspect/anormal/loader/DataCache.py
roxyai_inspect/anormal/loader/DataGenerator.py
roxyai_inspect/anormal/loader/DataLoader.py
roxyai_inspect/anormal/loader/DataLoader.tf.Data.py
roxyai_inspect/anormal/loader/DataSelectStrategy.py
roxyai_inspect/anormal/loader/__init__.py
roxyai_inspect/anormal/loader/augmix/__init__.py
roxyai_inspect/anormal/loader/augmix/augmix.py
roxyai_inspect/anormal/loader/augmix/helpers.py
roxyai_inspect/anormal/loader/augmix/transformations.py
roxyai_inspect/anormal/matcher/AnnoPredMatcher.py
roxyai_inspect/anormal/matcher/MatcherForSearch.py
roxyai_inspect-1.13.1.post1.dist-info/METADATA
roxyai_inspect-1.13.1.post1.dist-info/WHEEL
roxyai_inspect-1.13.1.post1.dist-info/entry_points.txt
roxyai_inspect-1.13.1.post1.dist-info/license(Dev-00R00214).lic
roxyai_inspect-1.13.1.post1.dist-info/top_level.txt
roxyai_inspect-1.13.1.post1.dist-info/RECORD
