Metadata-Version: 2.1
Name: roxyai-inspect
Version: 1.13.1.post1
Summary: Roxy AI Inspect-Server package
Home-page: https://gitlab.com/roxy-ai/roxy-ai
Author: Roxy Corp.
Author-email: support@roxy-ai.jp
License: Proprietary
Platform: UNKNOWN
Classifier: Programming Language :: Python :: 3.7
Classifier: License :: Other/Proprietary License
Classifier: Operating System :: OS Independent
Requires-Dist: numpy (==1.19.3)
Requires-Dist: imageio (==2.8.0)
Requires-Dist: pandas (==1.0.3)
Requires-Dist: scikit-learn (==0.22.2.post1)
Requires-Dist: matplotlib (==3.2.1)
Requires-Dist: xgboost (==1.0.2)
Requires-Dist: optuna (==1.2.0)
Requires-Dist: opencv-python (==4.2.0.34)
Requires-Dist: pyarmor (==6.1.0)
Requires-Dist: absl-py (==0.12.0)
Requires-Dist: alembic (==1.5.8)
Requires-Dist: astunparse (==1.6.3)
Requires-Dist: attrs (==20.3.0)
Requires-Dist: cachetools (==4.2.1)
Requires-Dist: certifi (==2020.12.5)
Requires-Dist: chardet (==4.0.0)
Requires-Dist: cliff (==3.7.0)
Requires-Dist: cloud-tpu-client (==0.10)
Requires-Dist: cmd2 (==1.5.0)
Requires-Dist: colorama (==0.4.4)
Requires-Dist: colorlog (==4.8.0)
Requires-Dist: cycler (==0.10.0)
Requires-Dist: flatbuffers (==1.12)
Requires-Dist: google-api-core (==1.31.5)
Requires-Dist: google-api-python-client (==1.8.0)
Requires-Dist: google-auth (==1.28.0)
Requires-Dist: google-auth-httplib2 (==0.1.0)
Requires-Dist: google-auth-oauthlib (==0.4.4)
Requires-Dist: google-pasta (==0.2.0)
Requires-Dist: googleapis-common-protos (==1.54.0)
Requires-Dist: graphviz (==0.16)
Requires-Dist: greenlet (==1.0.0)
Requires-Dist: grpcio (==1.32.0)
Requires-Dist: h5py (==2.10.0)
Requires-Dist: httplib2 (==0.20.2)
Requires-Dist: idna (==2.10)
Requires-Dist: importlib-metadata (==3.10.0)
Requires-Dist: importlib-resources (==5.4.0)
Requires-Dist: joblib (==1.0.1)
Requires-Dist: json5 (==0.9.5)
Requires-Dist: Keras-Preprocessing (==1.1.2)
Requires-Dist: kiwisolver (==1.3.1)
Requires-Dist: Mako (==1.1.4)
Requires-Dist: Markdown (==3.3.4)
Requires-Dist: MarkupSafe (==1.1.1)
Requires-Dist: oauthlib (==3.1.0)
Requires-Dist: objgraph (==3.5.0)
Requires-Dist: onnx (==1.10.1)
Requires-Dist: onnxoptimizer (==0.2.6)
Requires-Dist: onnxruntime-gpu (==1.9.0)
Requires-Dist: opt-einsum (==3.3.0)
Requires-Dist: packaging (==21.3)
Requires-Dist: pbr (==5.5.1)
Requires-Dist: Pillow (==8.1.2)
Requires-Dist: prettytable (==2.1.0)
Requires-Dist: protobuf (==3.15.6)
Requires-Dist: psutil (==5.8.0)
Requires-Dist: pyasn1 (==0.4.8)
Requires-Dist: pyasn1-modules (==0.2.8)
Requires-Dist: pyparsing (==2.4.7)
Requires-Dist: pyperclip (==1.8.2)
Requires-Dist: pyreadline (==2.1)
Requires-Dist: python-dateutil (==2.8.1)
Requires-Dist: python-editor (==1.0.4)
Requires-Dist: pytz (==2021.1)
Requires-Dist: PyYAML (==5.4.1)
Requires-Dist: pywin32 (==304)
Requires-Dist: requests (==2.25.1)
Requires-Dist: requests-oauthlib (==1.3.0)
Requires-Dist: rsa (==4.7.2)
Requires-Dist: Send2Trash (==1.5.0)
Requires-Dist: six (==1.15.0)
Requires-Dist: SQLAlchemy (==1.4.4)
Requires-Dist: stevedore (==3.3.0)
Requires-Dist: tensorboard-plugin-wit (==1.8.0)
Requires-Dist: tensorflow-estimator (==2.4.0)
Requires-Dist: termcolor (==1.1.0)
Requires-Dist: tf2onnx (==1.9.2)
Requires-Dist: tqdm (==4.59.0)
Requires-Dist: typeguard (==2.11.1)
Requires-Dist: typing-extensions (==3.7.4.3)
Requires-Dist: uritemplate (==3.0.1)
Requires-Dist: urllib3 (==1.26.4)
Requires-Dist: wcwidth (==0.2.5)
Requires-Dist: Werkzeug (==1.0.1)
Requires-Dist: wrapt (==1.12.1)
Requires-Dist: zipp (==3.4.1)
Requires-Dist: roxyai-api (>=1.13.0)
Provides-Extra: develop
Requires-Dist: pytest (==7.0.1) ; extra == 'develop'
Requires-Dist: wheel (==0.37.1) ; extra == 'develop'
Requires-Dist: twine (==3.8.0) ; extra == 'develop'
Requires-Dist: flake8 (==4.0.1) ; extra == 'develop'
Provides-Extra: tf21
Requires-Dist: gast (==0.2.2) ; extra == 'tf21'
Requires-Dist: scipy (==1.4.1) ; extra == 'tf21'
Requires-Dist: tensorboard (==2.1.1) ; extra == 'tf21'
Requires-Dist: tensorflow-gpu (==2.1.0) ; extra == 'tf21'
Requires-Dist: tensorflow-addons (==0.8.3) ; extra == 'tf21'
Provides-Extra: tf24
Requires-Dist: gast (==0.3.3) ; extra == 'tf24'
Requires-Dist: scipy (==1.6.2) ; extra == 'tf24'
Requires-Dist: tensorboard (==2.4.1) ; extra == 'tf24'
Requires-Dist: tensorflow-gpu (==2.4.0) ; extra == 'tf24'
Requires-Dist: tensorflow-addons (==0.12.0) ; extra == 'tf24'
